rich_dataframe/__init__.py
rich_dataframe/rich_dataframe.py
rich_dataframe-0.2.0.dist-info/LICENSE
rich_dataframe-0.2.0.dist-info/WHEEL
rich_dataframe-0.2.0.dist-info/METADATA
rich_dataframe-0.2.0.dist-info/RECORD
