Metadata-Version: 2.1
Name: rich-dataframe
Version: 0.2.0
Summary: Create animated and pretty Pandas Dataframe
Home-page: https://github.com/khuyentran1401/rich-dataframe
License: Apache-2.0
Keywords: pandas
Author: khuyentran1401
Author-email: khuyentran1476@gmail.com
Requires-Python: >=3.7.1,<4.0.0
Classifier: License :: OSI Approved :: Apache Software License
Classifier: Programming Language :: Python :: 3
Classifier: Programming Language :: Python :: 3.8
Classifier: Programming Language :: Python :: 3.9
Requires-Dist: pandas (>=1.2.2,<2.0.0)
Requires-Dist: rich (>=9.10.0,<10.0.0)
Requires-Dist: sklearn (>=0.0,<0.1)
Project-URL: Repository, https://github.com/khuyentran1401/rich-dataframe
